envsh/__init__.py
envsh/envsh-utils.sh
envsh/main.py
envsh/py.typed
envsh-0.1.4.dist-info/licenses/LICENSE
envsh-0.1.4.dist-info/METADATA
envsh-0.1.4.dist-info/WHEEL
envsh-0.1.4.dist-info/top_level.txt
envsh-0.1.4.dist-info/RECORD
