Metadata-Version: 2.4
Name: envsh
Version: 0.1.4
Summary: A Python library for loading environment variables from shell scripts with type-safe reading capabilities
Author: Envsh Contributors
Maintainer: Envsh Contributors
License: MIT
Project-URL: Homepage, https://github.com/TsybulkaM/envsh
Project-URL: Bug Reports, https://github.com/TsybulkaM/envsh/issues
Project-URL: Source, https://github.com/TsybulkaM/envsh
Project-URL: Documentation, https://github.com/TsybulkaM/envsh#readme
Keywords: environment,variables,shell,bash,configuration,env
Classifier: Development Status :: 4 - Beta
Classifier: Intended Audience :: Developers
Classifier: License :: OSI Approved :: MIT License
Classifier: Operating System :: POSIX :: Linux
Classifier: Operating System :: MacOS
Classifier: Operating System :: Unix
Classifier: Operating System :: Microsoft :: Windows
Classifier: Programming Language :: Python :: 3
Classifier: Programming Language :: Python :: 3.11
Classifier: Programming Language :: Python :: 3.12
Classifier: Topic :: Software Development :: Libraries :: Python Modules
Classifier: Topic :: System :: Systems Administration
Classifier: Topic :: Utilities
Classifier: Typing :: Typed
Requires-Python: >=3.11
License-File: LICENSE
Provides-Extra: dev
Requires-Dist: pytest>=6.0; extra == "dev"
Requires-Dist: pytest-cov>=2.0; extra == "dev"
Dynamic: license-file
